ewatercycle_lorenz/__init__.py
ewatercycle_lorenz/forcing.py
ewatercycle_lorenz/model.py
ewatercycle_lorenz-0.1.1.dist-info/METADATA
ewatercycle_lorenz-0.1.1.dist-info/WHEEL
ewatercycle_lorenz-0.1.1.dist-info/entry_points.txt
ewatercycle_lorenz-0.1.1.dist-info/licenses/LICENSE.txt
ewatercycle_lorenz-0.1.1.dist-info/RECORD
