Metadata-Version: 2.3
Name: ewatercycle-lorenz
Version: 0.1.1
Summary: Implementation of the lorenz-96 model for eWaterCycle
Project-URL: homepage, https://github.com/Daafip/ewatercycle-lorenz
Author-email: David Haasnoot <davidhaasnoot@gmail.com>
License-Expression: Apache-2.0
License-File: LICENSE.txt
Keywords: Data Assimilation,ewatercycle,hydrology
Classifier: Intended Audience :: Developers
Classifier: License :: OSI Approved :: Apache Software License
Classifier: Natural Language :: English
Classifier: Operating System :: OS Independent
Classifier: Programming Language :: Python
Classifier: Programming Language :: Python :: 3 :: Only
Requires-Dist: ewatercycle
